{
	"info": {
		"_postman_id": "c209a3a8-57f2-4924-b530-452f505f90dc",
		"name": "LARAVEL-API-DEMO",
		"schema": "https://schema.getpostman.com/json/collection/v2.1.0/collection.json",
		"_exporter_id": "33139208"
	},
	"item": [
		{
			"name": "Submit",
			"request": {
				"method": "POST",
				"header": [
					{
						"key": "Content-Type",
						"value": "application/json",
						"type": "text"
					}
				],
				"body": {
					"mode": "raw",
					"raw": "{\n      \"name\": \"John Doe\",\n     \n      \"message\": \"This is a test message.\"\n}",
					"options": {
						"raw": {
							"language": "json"
						}
					}
				},
				"url": {
					"raw": "{{api_base_url}}/submit",
					"host": [
						"{{api_base_url}}"
					],
					"path": [
						"submit"
					]
				}
			},
			"response": []
		}
	],
	"event": [
		{
			"listen": "prerequest",
			"script": {
				"type": "text/javascript",
				"exec": [
					""
				]
			}
		},
		{
			"listen": "test",
			"script": {
				"type": "text/javascript",
				"exec": [
					""
				]
			}
		}
	],
	"variable": [
		{
			"key": "api_base_url",
			"value": "http://127.0.0.1:8000/api",
			"type": "string"
		}
	]
}